nba_data_scraper/__init__.py
nba_data_scraper/_abstract.py
nba_data_scraper/_constants.py
nba_data_scraper/_data_scraper.py
nba_data_scraper/scraper.py
nba_data_scraper/utils/__init__.py
nba_data_scraper/utils/_logger.py
nba_data_scraper-1.0.1.dist-info/LICENSE
nba_data_scraper-1.0.1.dist-info/METADATA
nba_data_scraper-1.0.1.dist-info/WHEEL
nba_data_scraper-1.0.1.dist-info/RECORD
